{
  "title": "Chronomia",
  "artist": "Lime",
  "url" : "http://kanki2.net/",
	"bgColor": [
		"#ffffff",
		"#58e8ff"
  ],
  "bpm": 227,
  "startTime": 2150,
  "level": {
    "easy": -1,
    "normal": -1,
    "hard": 16
  },
  "map": {
    "easy": [
    ],
    "normal": [
    ],
    "hard": [
      "bc,,,,,,,,,,,,,,,",
      ",,,,,,,,,,,,,,,",
      "1fg,,,,,,,,,,,,,,,",
      "1,,,,,,4,,,,,,2,,3,",
      ",,2,,1,,,,,,,,,,,",
      "1,,,,2,,,,3,,,,4,,,",
      "1,,,,,,,,,,,,,,,",
      "1,,,,,,4,,,,,,3,,2,",
      ",,,,,,,,,,,,,,,",
      "1,,,,2,,,,3,,,,4,,,",
      "134,,,,,,,,,,,,,,,",
      "12,,,,,,23,,,,,,34,,,",
      "578,,,,,,568,,,,,,5678,,,",
      ",,,,,,,,,,,,12,,23,",
      "23,,,,,,34,,,,,,12,,,",
      "24,,,,,,23,,,,,,12,,,",
      "34,,,,,,,,,,,,13,,13,",
      ",,,,,,,,,,,,,,,",
      "568,,,,,,568,,,,,,578,,,",
      ",,578,,,,,,4,,2,3,1,2,3,",
      "1b,,,,1,,,,1,,,,1,,,",
      "1,,,,1,,,,1fc,,,,1,,,",
      "1bg,,,,1,,fc,,1,,,,1gd,,,",
      "1h,,,,12,,,,13,,,,14,,2,",
      "1d,,,,1,,ch,,1,,,,1bg,,,",
      "1,,,,1f,,,,12,,3,,14,,,",
      "14,,,,1,,3,,1,,,,13,,,",
      "1,,,,1,,34,,,,34,,56,78,56,78",
      "5b,,3,,1,,3,,1,,3,,1,,3,",
      "1,,3,,1,,3,,1fd,,3,,1,,3,",
      "12h,,3,,1,,34,,1,,3,,14,,3,",
      "1,,3,,12,,3,,14,,3,,14,,23,",
      "23,,4,,3,,14,,3,,4,,13,,4,",
      "3,,4,,3,,4,,13,,24,,23,,4,",
      "23,,4,,3,,14,,3,,4,,13,,34,",
      "1,,3,,1,2,3,4,1,2,3,4,4,3,2,1",
      "34,,1,,4,3,4,,3,,1,2,1,,2,",
      "4,3,4,,2,1,3,2,4,,3,,1,,2,",
      "4,,1,2,3,4,56,,,,78,,,,56,",
      ",,4,,3,,2,,1,,2,,3,,4,",
      "4,3,2,1,,,1,,1,,2,,3,,4,",
      ",,3,,,,2,3,4,3,2,1,1,2,3,4",
      "58,,23,,,,58,,,,,,58,,23,",
      ",,58,,1,2,3,4,1,2,3,4,1,2,3,4",
      "67,,1,,4,,67,,,,,,67,,1,",
      "4,1,2,3,4,1,2,3,4,1,2,3,4,1,2,3",
      "1,,,,123,,,,134,,,,124,,,",
      "134,,,,123,,,,123,,,,124,,,",
      "124,,,,1,,,,134,,,,123,,,",
      "123,,,,1,,,,123,,,,134,,,",
      "124,,,,1,,23,,1bc,,,,1,,,",
      "1,,,,1,,,,1,,,,1fg,,,",
      "1,,4,,13,,2,,14,,3,,12,,3,",
      "1,,4,,13,,2,,13,,4,,,,,",
      "1,4,2,3,568,,,,,,578,,,,,",
      "567,,,,,,678,,,,,,,,,",
      "2,3,1,4,567,,,,,,678,,,,,",
      "578,,,,,,568,,,,,,,,2,",
      "1,,2,,3,,4,,1,,2,,3,,4,",
      "1,,2,,3,,4,,1,,2,,3,,4,",
      "12,,,,,,23,,,,,,4,,,",
      "34,,,,,,,,3,,,,,,12,",
      "124,,,,,,,,,,,,,,,",
      "4,,,,,,,,,,,,,,,",
      "4,,,,,,,,1,,,,,,,",
      "2,,,,,,,,3,,,,,,,",
      "134,,2,,13,,2,,14,,3,,24,,3,",
      "134,,2,,13,,24,,14,,3,,124,,23,",
      "134,,23,,13,,2,,14,,3,,24,,3,",
      "124,,2,,123,,2,,134,,3,,234,,3,",
      "134,,2,,13,,2,,14,,3,,24,,3,",
      "124,,2,,13,,24,,14,,3,,234,,13,",
      "14,,2,,13,,2,,14,,3,,24,,3,",
      "134,,2,,13,,2,,124,,3,,234,,3,",
      "134,,2,,13,,2,,14,,3,,24,,3,",
      "134,,2,,13,,24,,14,,3,,234,,3,",
      "568,,,,,,578,,,,,,5bc8,,,",
      ",,,,,,,,fg,,,,2,,3,",
      "14,,2,,3,,12,,4,,3,,24,,3,",
      "14,,3,,2,,34,,1,,2,,13,,2,",
      "14,,2,,3,,2,,4,,3,,12,,13,",
      "4,,1,,4,,1,,4,,1,,24,,13,",
      "14,,2,,1,,23,,1,,2,,14,,2,",
      "13,,2,,1,,24,,1,,2,,1,,2,",
      "1d,,2,,1,,2ch,,1,,2,,1gd,,2,",
      "1ch,,2,,1,,2gd,,1,,2,,13h,,24,",
      "14,,2,,1,,23,,1,,2,,14,,2,",
      "13,,2,,1,,24,,1,,2,,13,,2,",
      "78,,2,,1,,56,,3,,4,,78,,2,",
      "1,,2,,78,,2,,1,,56,,3,,14,",
      "1,,,,,,,,,,,,,,,",
      "8,,,,,,,,,,,,2,,3,",
      "14,,2,,3,,4,,,,3,,4,,3,",
      "14,,2,,3,,4,,,,,,2,,3,",
      "1,,2,,3,,4,,,,,,,,,",
      "1,,,,,,,,,,1,,2,,3,",
      "14,,2,,3,,4,,,,1,,2,,(2,3,",
      ")14,,2,,3,,4,,3,,,,,,,",
      "14,,2,,3,,24,,,,,,1,,,",
      ",,,,,,,,,,,,,,,",
      "1,,,,1,,,,4,,,,1,,4,",
      "1,,4,,3,,2,,3,,,,2,,3,",
      "1,,,,1,,,,2,,3,,4,,,",
      "2,,3,,4,,,,1,,2,,3,,4,",
      "1,,1,,4,,2,3,2,3,2,,4,,1,",
      "4,,3,2,3,,1,,2,3,2,,4,,,",
      "a,,,,,,b,,,,,,cd,,,",
      ",,,,,,,,efgh,,,,2,,3,",
      "14,,2,,3,,2,,1,,23,,23,,12,",
      "13,,2,,3,,2,,1,,2,,23,,23,",
      "14,,2,,3,,2,,1,,2,,3,,2,",
      "1,,2,,3,,2,,1,,12,,23,,34,",
      "14,,3,,2,,3,,4,,34,,23,,23,",
      "14,,3,,2,,3,,24,,3,,2,,3,",
      "14,,3,,2,,34,,4,,3,,12,,3,",
      "4,,3,,2,,3,,4,,3,,2,,3,",
      "12,,3,,2,,3,,2,,3,,23,,23,",
      "12,,3,,2,,3,,2,,34,,12,,34,",
      "12,,3,,2,,3,,2,,3,,2,,3,",
      "2,,3,,2,,3,,2,,23,,23,,34,",
      "56,,,,,,78,,,,4,,563,,2,",
      "1,,,,78,,,,2,,56,,,,,",
      "d,,,,,,ch,,,,,,bg,,,",
      "1f,2,3,4,1,2,3,4,1,2,3,4,1,2,3,4",
      "12,,12,,,,12,,12,,,,12,,12,",
      ",,12,,12,,,,12,,12,,,,12,",
      "23,,,,23,,23,,,,23,,23,,,",
      "23,,23,,,,23,,23,,23,,23,,23,",
      ",,234,,234,,,,234,,234,,,,234,",
      "234,,,,234,,234,,,,234,,234,,,",
      "123,,123,,,,123,,123,,,,123,,123,",
      ",,5678,,5678,,5678,,5678,,5678,,5678,,5678,",
      ",,,,,,,,,,,,,,,",
      "1,,,,,,,,,,,,,,,",
      "3,,,,,,,,,,,,,,,",
      "(1,2,3,4,,,),,,,,,,,,,,"
    ]
  }
}